LICENSE
MANIFEST.in
README.rst
setup.py
cms_fragments/__init__.py
cms_fragments/acearea.py
cms_fragments/admin.py
cms_fragments/cms_plugins.py
cms_fragments/editarea.py
cms_fragments/models.py
cms_fragments/settings.py
cms_fragments/static/.DS_Store
cms_fragments/static/ace_start.js
cms_fragments/static/acecss/defaultace.css
cms_fragments/static/acejs/LICENSE
cms_fragments/static/acejs/ace-compat-noconflict.js
cms_fragments/static/acejs/ace-compat-uncompressed-noconflict.js
cms_fragments/static/acejs/ace-compat-uncompressed.js
cms_fragments/static/acejs/ace-compat.js
cms_fragments/static/acejs/ace-noconflict.js
cms_fragments/static/acejs/ace-uncompressed-noconflict.js
cms_fragments/static/acejs/ace-uncompressed.js
cms_fragments/static/acejs/ace.js
cms_fragments/static/acejs/keybinding-emacs-noconflict.js
cms_fragments/static/acejs/keybinding-emacs-uncompressed-noconflict.js
cms_fragments/static/acejs/keybinding-emacs-uncompressed.js
cms_fragments/static/acejs/keybinding-emacs.js
cms_fragments/static/acejs/keybinding-vim-noconflict.js
cms_fragments/static/acejs/keybinding-vim-uncompressed-noconflict.js
cms_fragments/static/acejs/keybinding-vim-uncompressed.js
cms_fragments/static/acejs/keybinding-vim.js
cms_fragments/static/acejs/mode-c_cpp-noconflict.js
cms_fragments/static/acejs/mode-c_cpp-uncompressed-noconflict.js
cms_fragments/static/acejs/mode-c_cpp-uncompressed.js
cms_fragments/static/acejs/mode-c_cpp.js
cms_fragments/static/acejs/mode-clojure-noconflict.js
cms_fragments/static/acejs/mode-clojure-uncompressed-noconflict.js
cms_fragments/static/acejs/mode-clojure-uncompressed.js
cms_fragments/static/acejs/mode-clojure.js
cms_fragments/static/acejs/mode-coffee-noconflict.js
cms_fragments/static/acejs/mode-coffee-uncompressed-noconflict.js
cms_fragments/static/acejs/mode-coffee-uncompressed.js
cms_fragments/static/acejs/mode-coffee.js
cms_fragments/static/acejs/mode-coldfusion-noconflict.js
cms_fragments/static/acejs/mode-coldfusion-uncompressed-noconflict.js
django_cms_fragments.egg-info/PKG-INFO
django_cms_fragments.egg-info/SOURCES.txt
django_cms_fragments.egg-info/dependency_links.txt
django_cms_fragments.egg-info/not-zip-safe
django_cms_fragments.egg-info/top_level.txt