Metadata-Version: 1.0
Name: django-cms-fragments
Version: 0.0.5
Summary: Injecting fragments of js, css and html in a django-cms plugin
Home-page: https://github.com/bianchimro/django-cms-fragments
Author: Mauro Bianchi
Author-email: bianchimro@gmail.com
License: BSD
Platform: UNKNOWN
Classifier: Development Status :: 3 - Alpha
Classifier: Environment :: Web Environment
Classifier: Intended Audience :: Developers
Classifier: License :: OSI Approved :: BSD License
Classifier: Operating System :: OS Independent
Classifier: Programming Language :: Python
Classifier: Topic :: Internet :: WWW/HTTP :: Dynamic Content
Classifier: Framework :: Django
